pyrsing/__init__.py
pyrsing/sql.py
pyrsing-1.0.0rc2.dist-info/LICENSE
pyrsing-1.0.0rc2.dist-info/METADATA
pyrsing-1.0.0rc2.dist-info/WHEEL
pyrsing-1.0.0rc2.dist-info/top_level.txt
pyrsing-1.0.0rc2.dist-info/RECORD
