Metadata-Version: 2.1
Name: pyrsing
Version: 1.0.0rc2
Summary: A parsing tool.
Home-page: https://github.com/samuelcorradi/pyrsing
Author: Samuel Corradi
Author-email: samuelcorradi@gmail.com
License: UNKNOWN
Platform: UNKNOWN
Classifier: Programming Language :: Python :: 3
Classifier: License :: OSI Approved :: Apache Software License
Classifier: Operating System :: OS Independent
Classifier: Programming Language :: SQL
Classifier: Topic :: Text Processing :: General
Classifier: Topic :: Utilities
Classifier: Topic :: Database
Requires-Python: >=3.7.8
License-File: LICENSE
